Metadata-Version: 2.1
Name: drf-friendly-errors-mod
Version: 0.13.10
Summary: Extension for displaying serializer validation errors in Django Rest Framework
Home-page: UNKNOWN
Author: Tomasz Łaszczuk
Author-email: t.laszczuk@futuremind.com
License: MIT
Platform: UNKNOWN
Classifier: Environment :: Web Environment
Classifier: Framework :: Django
Classifier: License :: OSI Approved :: MIT License
Classifier: Intended Audience :: Developers
Classifier: Operating System :: OS Independent
Classifier: Programming Language :: Python
Classifier: Programming Language :: Python :: 3
Classifier: Topic :: Internet :: WWW/HTTP
